CHANGES.rst
MANIFEST.in
README.rst
setup.cfg
setup.py
kotti_disqus/__init__.py
kotti_disqus/populate.py
kotti_disqus/views.py
kotti_disqus.egg-info/PKG-INFO
kotti_disqus.egg-info/SOURCES.txt
kotti_disqus.egg-info/dependency_links.txt
kotti_disqus.egg-info/not-zip-safe
kotti_disqus.egg-info/requires.txt
kotti_disqus.egg-info/top_level.txt
kotti_disqus/locale/README
kotti_disqus/locale/kotti_disqus.pot
kotti_disqus/locale/en/LC_MESSAGES/kotti_disqus.mo
kotti_disqus/locale/en/LC_MESSAGES/kotti_disqus.po
kotti_disqus/locale/sl/LC_MESSAGES/kotti_disqus.mo
kotti_disqus/locale/sl/LC_MESSAGES/kotti_disqus.po
kotti_disqus/templates/disqus_comments.pt