Metadata-Version: 1.1
Name: kotti-disqus
Version: 0.1
Summary: Disqus commenting system add-on for Kotti
Home-page: https://github.com/nightmarebadger/kotti_disqus
Author: Natan Žabkar
Author-email: natan.zabkar@gmail.com
License: BSD
Keywords: kotti add-on
Platform: UNKNOWN
Classifier: Environment :: Web Environment
Classifier: Framework :: Pylons
Classifier: Framework :: Pyramid
Classifier: Intended Audience :: Developers
Classifier: License :: OSI Approved :: BSD License
Classifier: Operating System :: OS Independent
Classifier: Programming Language :: Python
Classifier: Programming Language :: Python :: 2.6
Classifier: Programming Language :: Python :: 2.7
Classifier: Topic :: Internet :: WWW/HTTP
Classifier: Topic :: Software Development :: User Interfaces
